{
  "category": "animals",
  "displayName": "動物",
  "images": [
    "baby-chiken-01", "baby-chiken-02", "bird-01", "butterfly-01", "butterfly-02",
    "cat-01", "cat-02", "cat-03", "cat-04", "chiken-01",
    "cow-01", "dog-01", "dog-02", "elephant-01",
    "fish-01", "fish-02", "fox-01", "giraffe-01", "gorilla-01",
    "lion-01", "monkey-01", "monkey-02", "pig-02", "turtle-01"
  ],
  "sounds": [
    "baby-chiken", "bird", "butterfly", "cat", "chiken", "cow", "dog", "elephant",
    "fish", "fox", "giraffe", "gorilla", "lion", "monkey", "pig", "turtle"
  ],
  "audioMap": {
    "baby-chiken-01": "baby-chiken",
    "baby-chiken-02": "baby-chiken",
    "bird-01": "bird",
    "butterfly-01": "butterfly",
    "butterfly-02": "butterfly",
    "cat-01": "cat",
    "cat-02": "cat",
    "cat-03": "cat",
    "cat-04": "cat",
    "chiken-01": "chiken",
    "cow-01": "cow",
    "dog-01": "dog",
    "dog-02": "dog",
    "elephant-01": "elephant",
    "fish-01": "fish",
    "fish-02": "fish",
    "fox-01": "fox",
    "giraffe-01": "giraffe",
    "gorilla-01": "gorilla",
    "lion-01": "lion",
    "monkey-01": "monkey",
    "monkey-02": "monkey",
    "pig-02": "pig",
    "turtle-01": "turtle"
  },
  "assetPaths": {
    "images": "illust/animals/",
    "sounds": "voice/animals/"
  },
  "fileExtensions": {
    "images": ".png",
    "sounds": ".wav"
  }
}